hitfactorpy/__init__.py
hitfactorpy/__main__.py
hitfactorpy/cli.py
hitfactorpy/client.py
hitfactorpy/decimal_.py
hitfactorpy/enums.py
hitfactorpy/parsers/__init__.py
hitfactorpy/parsers/csv_utils.py
hitfactorpy/parsers/match_report/__init__.py
hitfactorpy/parsers/match_report/constants.py
hitfactorpy/parsers/match_report/fields.py
hitfactorpy/parsers/match_report/match_info.py
hitfactorpy/parsers/match_report/models.py
hitfactorpy/parsers/match_report/pandas/README.md
hitfactorpy/parsers/match_report/pandas/__init__.py
hitfactorpy/parsers/match_report/pandas/competitor.py
hitfactorpy/parsers/match_report/pandas/dataframe.py
hitfactorpy/parsers/match_report/pandas/report_sections.py
hitfactorpy/parsers/match_report/pandas/stage.py
hitfactorpy/parsers/match_report/pandas/stage_score.py
hitfactorpy/parsers/match_report/strict/README.md
hitfactorpy/parsers/match_report/strict/__init__.py
hitfactorpy/parsers/match_report/strict/competitor.py
hitfactorpy/parsers/match_report/strict/report_lines.py
hitfactorpy/parsers/match_report/strict/stage.py
hitfactorpy/parsers/match_report/strict/stage_score.py
hitfactorpy/py.typed
hitfactorpy/pydantic_/__init__.py
hitfactorpy/pydantic_/models.py
hitfactorpy/utils.py
hitfactorpy-1.0.1.dist-info/METADATA
hitfactorpy-1.0.1.dist-info/WHEEL
hitfactorpy-1.0.1.dist-info/entry_points.txt
hitfactorpy-1.0.1.dist-info/RECORD
